attending_machine/__init__.py
attending_machine-0.0.1.dist-info/LICENSE
attending_machine-0.0.1.dist-info/METADATA
attending_machine-0.0.1.dist-info/WHEEL
attending_machine-0.0.1.dist-info/top_level.txt
attending_machine-0.0.1.dist-info/RECORD
