Metadata-Version: 2.1
Name: attending-machine
Version: 0.0.1
Summary: Attending Machine
Author-email: Alexander Fedotov <alex.fedotov@aol.com>
Project-URL: Homepage, https://github.com/attending-machine/attending-machine
Project-URL: Bug Tracker, https://github.com/attending-machine/attending-machine/issues
Classifier: Programming Language :: Python :: 3
Classifier: License :: OSI Approved :: MIT License
Classifier: Operating System :: OS Independent
Requires-Python: >=3.10
License-File: LICENSE
